{
  "product": "M1486630956RE",
  "pds_dataset_name": "LRO-L-LROC-2-EDR-V1.0",
  "pds_volume_name": "LROLRC_0061C",
  "instrument_host": "LRO",
  "instrument": "LROC",
  "original_product": "nacr003181cb",
  "product_version": "v1.8",
  "mission_phase_name": "FIFTH EXTENDED SCIENCE MISSION",
  "rationale_desc": "TARGET OF OPPORTUNITY",
  "data_quality": 0,
  "timing": {
    "nac_preroll_start_time": "2024-11-19T04:48:08",
    "start_time": "2024-11-19T04:48:09",
    "stop_time": "2024-11-19T04:48:15",
    "spacecraft_clock_partition": 1,
    "nac_spacecraft_clock_preroll_count": "753684488:49545",
    "spacecraft_clock_start_count": "753684489:17121",
    "spacecraft_clock_stop_count": "753684495:54363"
  },
  "target": {
    "name": "MOON",
    "orbit_number": 69315,
    "slew_angle": 0.011381402260907227,
    "lro_node_crossing": "A",
    "lro_flight_direction": "-X"
  },
  "instrument_settings": {
    "nac_line_exposure_duration": 0.0004912,
    "nac_frame": "RIGHT",
    "nac_dac_reset": 200,
    "nac_channel_a_offset": 44,
    "nac_channel_b_offset": 107,
    "instrument_mode_code": 7,
    "compand_select_code": 3,
    "mode_compression": true,
    "mode_test": false
  },
  "temperatures": {
    "nac_temperature_scs": 5.339,
    "nac_temperature_fpa": 19.224,
    "nac_temperature_fpga": -10.628,
    "nac_temperature_telescope": 9.15
  },
  "image_properties": {
    "image_lines": 13312,
    "line_samples": 5064,
    "sample_bits": 8,
    "scaled_pixel_width": 0.72,
    "scaled_pixel_height": 0.78,
    "resolution": 0.748900072216212
  },
  "geometry": {
    "emission_angle": 1.77,
    "incidence_angle": 47.43,
    "phase_angle": 49.08,
    "north_azimuth": 83.08,
    "sub_solar_azimuth": 203.03,
    "sub_solar_latitude": -1.27,
    "sub_solar_longitude": 322.81,
    "sub_spacecraft_latitude": 25.87,
    "sub_spacecraft_longitude": 3.27,
    "solar_distance": 148107424.7,
    "solar_longitude": 234.88
  },
  "coverage": {
    "center_latitude": 25.86,
    "center_longitude": 3.19,
    "upper_right_latitude": 26.04,
    "upper_right_longitude": 3.24,
    "lower_right_latitude": 25.7,
    "lower_right_longitude": 3.28,
    "lower_left_latitude": 25.69,
    "lower_left_longitude": 3.15,
    "upper_left_latitude": 26.03,
    "upper_left_longitude": 3.11
  },
  "spacecraft": {
    "altitude": 71.6,
    "target_center_distance": 1808.91
  }
}
